act/__init__.py
act/act_types.py
act/analysis.py
act/builder.py
act/cell_model.py
act/logger.py
act/metrics.py
act/models.py
act/optim.py
act/simulator.py
act/target_utils.py
legacy/feature_model.py
legacy/optim.py
simulation/analyze_res.py
simulation/run_simulation.py
simulation/simulation_configs.py
act_neuron-0.1.9.dist-info/METADATA
act_neuron-0.1.9.dist-info/WHEEL
act_neuron-0.1.9.dist-info/licenses/LICENSE
act_neuron-0.1.9.dist-info/RECORD
