Metadata-Version: 2.1
Name: act-neuron
Version: 0.1.9
Summary: Automatic Cell Tuner
License-File: LICENSE
Requires-Python: >=3.8
Requires-Dist: h5py
Requires-Dist: matplotlib
Requires-Dist: neuron>=8.2.0
Requires-Dist: numpy
Requires-Dist: torch
